aiidalab_qe_base/__init__.py
aiidalab_qe_base/mixins.py
aiidalab_qe_base/utils.py
aiidalab_qe_base/models/__init__.py
aiidalab_qe_base/models/code.py
aiidalab_qe_base/models/model.py
aiidalab_qe_base/panels/__init__.py
aiidalab_qe_base/panels/configuration/__init__.py
aiidalab_qe_base/panels/configuration/configuration.py
aiidalab_qe_base/panels/configuration/model.py
aiidalab_qe_base/panels/panel/__init__.py
aiidalab_qe_base/panels/panel/model.py
aiidalab_qe_base/panels/panel/panel.py
aiidalab_qe_base/panels/resources/__init__.py
aiidalab_qe_base/panels/resources/model.py
aiidalab_qe_base/panels/resources/resources.py
aiidalab_qe_base/panels/results/__init__.py
aiidalab_qe_base/panels/results/model.py
aiidalab_qe_base/panels/results/results.py
aiidalab_qe_base/panels/settings/__init__.py
aiidalab_qe_base/panels/settings/model.py
aiidalab_qe_base/panels/settings/settings.py
aiidalab_qe_base/plugin/__init__.py
aiidalab_qe_base/plugin/outline.py
aiidalab_qe_base/plugin/panels/resources/__init__.py
aiidalab_qe_base/plugin/panels/resources/model.py
aiidalab_qe_base/plugin/panels/resources/resources.py
aiidalab_qe_base/widgets/__init__.py
aiidalab_qe_base/widgets/widgets.py
aiidalab_qe_base/widgets/table_widget/__init__.py
aiidalab_qe_base/widgets/table_widget/table_widget.css
aiidalab_qe_base/widgets/table_widget/table_widget.js
aiidalab_qe_base/widgets/table_widget/table_widget.py
aiidalab_qe_base-0.2.0.dist-info/entry_points.txt
aiidalab_qe_base-0.2.0.dist-info/licenses/LICENSE
aiidalab_qe_base-0.2.0.dist-info/WHEEL
aiidalab_qe_base-0.2.0.dist-info/METADATA
aiidalab_qe_base-0.2.0.dist-info/RECORD
