Metadata-Version: 2.4
Name: aiidalab-qe-base
Version: 0.2.0
Summary: Utilities, widgets, and components shared by the AiiDAlab Quantum ESPRESSO app and its plugins
Author-email: AiiDAlab team <aiidalab@materialscloud.org>
Requires-Python: >=3.9
License-File: LICENSE
Requires-Dist: aiida-core~=2.5,<3
Requires-Dist: aiidalab-widgets-base~=2.4.0
Requires-Dist: aiida-quantumespresso~=4.12.0
Requires-Dist: anywidget==0.9.13
Requires-Dist: table_widget~=0.0.2
Requires-Dist: pre-commit~=3.2 ; extra == "dev"
Requires-Dist: pytest~=7.4 ; extra == "test"
Requires-Dist: pytest-cov~=5.0 ; extra == "test"
Project-URL: Homepage, https://github.com/aiidalab/aiidalab-qe-base
Project-URL: Repository, https://github.com/aiidalab/aiidalab-qe-base
Provides-Extra: dev
Provides-Extra: test
